stitch_demo/__init__.py
stitch_demo/demo.py
nailfold_stitch-1.0.0.dist-info/METADATA
nailfold_stitch-1.0.0.dist-info/WHEEL
nailfold_stitch-1.0.0.dist-info/top_level.txt
nailfold_stitch-1.0.0.dist-info/RECORD
