Metadata-Version: 2.1
Name: nailfold-stitch
Version: 1.0.0
Summary: This is my first Python SDK, intended for testing packaging.
Home-page: https://github.com/你的仓库地址
Author: Jianan Lin
Author-email: 1614875545@qq.com
Classifier: Programming Language :: Python :: 3
Classifier: License :: OSI Approved :: MIT License
Classifier: Operating System :: OS Independent
Requires-Python: >=3.4
Requires-Dist: requests >=2.28.0
Requires-Dist: pandas >=1.1.5
Requires-Dist: numpy >=1.19.5
